COPYING
MANIFEST.in
Makefile
README.md
requirements.txt
setup.py
envelop/__init__.py
envelop/__main__.py
envelop.egg-info/PKG-INFO
envelop.egg-info/SOURCES.txt
envelop.egg-info/dependency_links.txt
envelop.egg-info/requires.txt
envelop.egg-info/top_level.txt