Metadata-Version: 1.0
Name: envelop
Version: 0.2.0
Summary: A helping hand to manage your settings among different environments
Home-page: https://github.com/Yipit/envelop
Author: Lincoln de Sousa
Author-email: lincoln@yipit.com
License: UNKNOWN
Platform: UNKNOWN
